{
    "version": "1.20.3",
    "description": "Easy-to-use command-line/curses/web plaintext accounting tool",
    "homepage": "https://hledger.org/",
    "license": "GPL-3.0",
    "architecture": {
        "64bit": {
            "url": "https://github.com/simonmichael/hledger/releases/download/1.20.3/hledger-windows.zip",
            "hash": "c1a8c77716fe912da4a627ed4a5b6887571d3b5338c0638e47eb6ba35d2df5e2"
        }
    },
    "bin": [
        "hledger.exe",
        "hledger-web.exe"
    ],
    "checkver": {
        "github": "https://github.com/simonmichael/hledger"
    },
    "autoupdate": {
        "architecture": {
            "64bit": {
                "url": "https://github.com/simonmichael/hledger/releases/download/$version/hledger-windows.zip"
            }
        }
    }
}
